efjtk/__init__.py
efjtk/cli.py
efjtk/config.py
efjtk/convert.py
efjtk/gui.py
efjtk/logbook-template.html
efjtk/modify.py
efjtk/summary-template.html
efjtk-0.9.1.dist-info/LICENSE
efjtk-0.9.1.dist-info/METADATA
efjtk-0.9.1.dist-info/WHEEL
efjtk-0.9.1.dist-info/entry_points.txt
efjtk-0.9.1.dist-info/top_level.txt
efjtk-0.9.1.dist-info/RECORD
