Metadata-Version: 2.1
Name: efjtk
Version: 0.9.1
Summary: Convert EFJ files into FCL compliant logbooks and more
Home-page: https://github.com/JonHurst/efjtk
Author: Jon Hurst
Author-email: jon.a@hursts.org.uk
Project-URL: docs, https://hursts.org.uk/efjtkdocs/
Classifier: Development Status :: 4 - Beta
Classifier: Environment :: Console
Classifier: Programming Language :: Python :: 3
Classifier: License :: OSI Approved :: GNU General Public License v3 or later (GPLv3+)
Classifier: Operating System :: OS Independent
Requires-Python: >=3.11
License-File: LICENSE
Requires-Dist: nightflight >=0.9
Requires-Dist: efj-parser >=0.9.2
